mlscale/__init__.py
mlscale/main.py
ScaleML-0.2.0.dist-info/METADATA
ScaleML-0.2.0.dist-info/WHEEL
ScaleML-0.2.0.dist-info/top_level.txt
ScaleML-0.2.0.dist-info/RECORD
